django_orghierarchy/__init__.py
django_orghierarchy/admin.py
django_orghierarchy/api.py
django_orghierarchy/apps.py
django_orghierarchy/forms.py
django_orghierarchy/importers.py
django_orghierarchy/models.py
django_orghierarchy/utils.py
django_orghierarchy/management/__init__.py
django_orghierarchy/management/commands/__init__.py
django_orghierarchy/management/commands/import_organizations.py
django_orghierarchy/migrations/0001_initial.py
django_orghierarchy/migrations/0002_organization_replaced_by.py
django_orghierarchy/migrations/0003_rm_responsible_org_add_internal_type.py
django_orghierarchy/migrations/0004_add_affiliated_org_permissions.py
django_orghierarchy/migrations/0005_add_fields_to_organization_class.py
django_orghierarchy/migrations/0006_add_user_editable_to_data_source.py
django_orghierarchy/migrations/0007_set_editable_false_on_mptt_fields.py
django_orghierarchy/migrations/0008_modify_organization_on_deletes.py
django_orghierarchy/migrations/0009_add_change_organization_regular_users_permission.py
django_orghierarchy/migrations/0010_rename_user_editable.py
django_orghierarchy/migrations/0011_alter_datasource_user_editable_organizations.py
django_orghierarchy/migrations/0012_alter_organization_unique_together_and_more.py
django_orghierarchy/migrations/0013_add_organization_indexes.py
django_orghierarchy/migrations/__init__.py
django_orghierarchy-0.6.2.dist-info/licenses/LICENSE
django_orghierarchy-0.6.2.dist-info/METADATA
django_orghierarchy-0.6.2.dist-info/WHEEL
django_orghierarchy-0.6.2.dist-info/top_level.txt
django_orghierarchy-0.6.2.dist-info/RECORD
